README.rst
setup.py
pyrediq/__init__.py
pyrediq/priority_queue.py
pyrediq.egg-info/PKG-INFO
pyrediq.egg-info/SOURCES.txt
pyrediq.egg-info/dependency_links.txt
pyrediq.egg-info/pbr.json
pyrediq.egg-info/requires.txt
pyrediq.egg-info/top_level.txt