Metadata-Version: 1.1
Name: pyrediq
Version: 0.2.0
Summary: Priority message queue with Redis
Home-page: https://github.com/okomestudio/pyrediq
Author: Taro Sato
Author-email: okomestudio@gmail.com
License: MIT
Platform: Linux
Classifier: Development Status :: 3 - Alpha
Classifier: Intended Audience :: Developers
Classifier: License :: OSI Approved :: MIT License
Classifier: Operating System :: POSIX :: Linux
Classifier: Programming Language :: Python :: 2.7
Classifier: Topic :: System :: Distributed Computing
